rkan/__init__.py
rkan/jacobi_polynomials.py
rkan/tensorflow.py
rkan/torch.py
rkan-0.0.3.dist-info/LICENSE
rkan-0.0.3.dist-info/METADATA
rkan-0.0.3.dist-info/WHEEL
rkan-0.0.3.dist-info/top_level.txt
rkan-0.0.3.dist-info/RECORD
